py3enc/__init__.py
py3enc/py3enc.py
py3enc-1.0.0.dist-info/LICENSE
py3enc-1.0.0.dist-info/METADATA
py3enc-1.0.0.dist-info/WHEEL
py3enc-1.0.0.dist-info/top_level.txt
py3enc-1.0.0.dist-info/RECORD
