Metadata-Version: 2.1
Name: py3enc
Version: 1.0.0
Summary: Simple module forn encrypt python3 scripts.
Home-page: https://github.com/0xakxvau
Author: 0xakxvau
Author-email: 0xakxvau@gmail.com
License: MIT
Keywords: python,pyenc,encpy,python encrypt,python encryption,encpy python,py3enc
Classifier: Development Status :: 4 - Beta
Classifier: Intended Audience :: Developers
Classifier: Topic :: Software Development :: Libraries :: Python Modules
Classifier: License :: OSI Approved :: MIT License
Classifier: Programming Language :: Python :: 3
Classifier: Operating System :: OS Independent
Classifier: Environment :: Console
Requires-Python: >=3.9.5
License-File: LICENSE
Requires-Dist: pytz
